Metadata-Version: 1.1
Name: scintillations
Version: 0.1.0
Summary: Generate sequences of scintillations
Home-page: UNKNOWN
Author: Frederik Rietdijk
Author-email: freddyrietdijk@fridh.nl
License: LICENSE
Platform: UNKNOWN
Classifier: License :: OSI Approved :: BSD License
Classifier: Programming Language :: Python :: 3 :: Only
Classifier: Programming Language :: Python :: 3.5
Classifier: Topic :: Scientific/Engineering
